LICENSE
MANIFEST.in
README.rst
setup.py
django_linked_accounts.egg-info/PKG-INFO
django_linked_accounts.egg-info/SOURCES.txt
django_linked_accounts.egg-info/dependency_links.txt
django_linked_accounts.egg-info/requires.txt
django_linked_accounts.egg-info/top_level.txt
linked_accounts/__init__.py
linked_accounts/admin.py
linked_accounts/authentication.py
linked_accounts/backends.py
linked_accounts/forms.py
linked_accounts/handlers.py
linked_accounts/models.py
linked_accounts/signals.py
linked_accounts/urls.py
linked_accounts/utils.py
linked_accounts/views.py
linked_accounts/management/__init__.py
linked_accounts/management/commands/__init__.py
linked_accounts/management/commands/convert_rpx.py
linked_accounts/templatetags/__init__.py
linked_accounts/templatetags/linked_accounts_tags.py