Metadata-Version: 1.1
Name: django-linked-accounts
Version: 2.1.2
Summary: Link third-party service accounts to Django accounts.
Home-page: http://github.com/zen4ever/django-linked-accounts
Author: Andrii Kurinnyi
Author-email: andrew@zen4ever.com
License: UNKNOWN
Keywords: django,oauth,accounts,twitter,facebook
Platform: UNKNOWN
Classifier: Development Status :: 1 - Planning
Classifier: Programming Language :: Python
Classifier: Intended Audience :: Developers
Classifier: License :: OSI Approved :: MIT License
Classifier: Operating System :: OS Independent
Classifier: Framework :: Django
